scan/__init__.py
scan/artifact.py
scan/cli.py
scan/collect.py
scan/diagnose.py
scan/summary.py
scan/tree.py
scan/warn.py
tscodescan-0.4.0.dist-info/METADATA
tscodescan-0.4.0.dist-info/WHEEL
tscodescan-0.4.0.dist-info/entry_points.txt
tscodescan-0.4.0.dist-info/top_level.txt
tscodescan-0.4.0.dist-info/RECORD
