Metadata-Version: 2.4
Name: tscodescan
Version: 0.4.0
Summary: repository artifact generator
Requires-Python: >=3.8
Dynamic: requires-python
Dynamic: summary
